MANIFEST.in
README.md
setup.cfg
setup.py
atavism/__init__.py
atavism/chromecast.py
atavism/command_line.py
atavism/devices.py
atavism/dnssd.py
atavism/http.py
atavism/video.py
atavism.egg-info/PKG-INFO
atavism.egg-info/SOURCES.txt
atavism.egg-info/dependency_links.txt
atavism.egg-info/entry_points.txt
atavism.egg-info/requires.txt
atavism.egg-info/top_level.txt
atavism/http11/__init__.py
atavism/http11/base.py
atavism/http11/client.py
atavism/http11/content.py
atavism/http11/cookies.py
atavism/http11/headers.py
atavism/http11/objects.py
atavism/http11/range.py
atavism/http11/server.py