Metadata-Version: 1.1
Name: atavism
Version: 0.2
Summary: Module to play video to an AppleTV
Home-page: https://github.com/zathras777/atavism
Author: david reid
Author-email: zathrasorama@gmail.com
License: Unlicense
Download-URL: https://github.com/zathras777/atavism/tarball/0.2
Keywords: appletv video ffmpeg streaming
Platform: UNKNOWN
Classifier: Development Status :: 3 - Alpha
Classifier: Intended Audience :: Developers
Classifier: Topic :: Software Development :: Libraries :: Python Modules
Classifier: Topic :: Multimedia :: Video :: Display
Classifier: Programming Language :: Python :: 2.7
Classifier: Programming Language :: Python :: 3.4
